streamlit_ocean_compute/__init__.py
streamlit_ocean_compute-0.0.3.dist-info/LICENSE
streamlit_ocean_compute-0.0.3.dist-info/METADATA
streamlit_ocean_compute-0.0.3.dist-info/WHEEL
streamlit_ocean_compute-0.0.3.dist-info/top_level.txt
streamlit_ocean_compute-0.0.3.dist-info/RECORD
