Metadata-Version: 2.1
Name: streamlit-ocean-compute
Version: 0.0.3
Summary: Streamlit component for running compute-to-data with Ocean Protocol
Home-page: UNKNOWN
Author: AlgoveraAI
Author-email: hello@algovera.ai
License: UNKNOWN
Platform: UNKNOWN
Requires-Python: >=3.6
License-File: LICENSE
Requires-Dist: streamlit (>=0.63)
Requires-Dist: streamlit-wallet-connect
